Metadata-Version: 1.1
Name: melopero-samm8q
Version: 0.0.1
Summary: A module to easily access samm8q gps features
Home-page: https://github.com/melopero/Melopero_SAM-M8Q
Author: Melopero
Author-email: info@melopero.com
License: MIT
Platform: UNKNOWN
Classifier: Development Status :: 3 - Alpha
Classifier: License :: OSI Approved :: MIT License
Classifier: Programming Language :: Python :: 3
Classifier: Programming Language :: Python :: 3.5
